py_origami_editor_3d/__init__.py
py_origami_editor_3d/commands.py
py_origami_editor_3d/origami.py
py_origami_editor_3d/paper_types.py
py_origami_editor_3d-0.1.0.dist-info/LICENSE
py_origami_editor_3d-0.1.0.dist-info/METADATA
py_origami_editor_3d-0.1.0.dist-info/WHEEL
py_origami_editor_3d-0.1.0.dist-info/top_level.txt
py_origami_editor_3d-0.1.0.dist-info/RECORD
