Metadata-Version: 2.1
Name: py-origami-editor-3d
Version: 0.1.0
Summary: Python preprocessing tool to create OrigamiScript input files for Origami Editor 3D
Home-page: https://gitlab.com/stranskyjan/py-origami-editor-3d
Author: Jan Stránský
Author-email: honzik.stransky@gmail.com
License: UNKNOWN
Project-URL: Bug Tracker, https://gitlab.com/stranskyjan/py-origami-editor-3d/-/issues
Platform: UNKNOWN
Classifier: Programming Language :: Python :: 3
Classifier: License :: OSI Approved :: MIT License
Classifier: Operating System :: OS Independent
Requires-Python: >=3.10
License-File: LICENSE
